magnum_opus/__init__.py
magnum_opus/operarius.py
magnum_opus-3.1.dist-info/METADATA
magnum_opus-3.1.dist-info/WHEEL
magnum_opus-3.1.dist-info/licenses/LICENSE
magnum_opus-3.1.dist-info/RECORD
