Metadata-Version: 2.3
Name: magnum-opus
Version: 3.1
Summary: An extendable general purpose task manager or workflow engine.
Project-URL: Homepage, https://github.com/nicc777/magnum-opus
Project-URL: Documentation, https://github.com/nicc777/magnum-opus
Project-URL: Repository, https://github.com/nicc777/magnum-opus
Project-URL: Issues, https://github.com/nicc777/magnum-opus/issues
Project-URL: Changelog, https://raw.githubusercontent.com/nicc777/magnum-opus/main/CHANGELOG.md
Author-email: Nico Coetzee <nicc777@gmail.com>
Maintainer-email: Nico Coetzee <nicc777@gmail.com>
License: MIT License
License-File: LICENSE
Classifier: Development Status :: 3 - Alpha
Classifier: Intended Audience :: Developers
Classifier: License :: OSI Approved :: MIT License
Classifier: Programming Language :: Python :: 3
Classifier: Programming Language :: Python :: 3.10
Classifier: Programming Language :: Python :: 3.11
Classifier: Programming Language :: Python :: 3.12
Classifier: Programming Language :: Python :: 3.13
Requires-Python: >=3.10
